sharepoint2text/__init__.py
sharepoint2text/cli.py
sharepoint2text/py.typed
sharepoint2text/parsing/__init__.py
sharepoint2text/parsing/exceptions.py
sharepoint2text/parsing/mime_types.py
sharepoint2text/parsing/router.py
sharepoint2text/parsing/extractors/__init__.py
sharepoint2text/parsing/extractors/archive_extractor.py
sharepoint2text/parsing/extractors/data_types.py
sharepoint2text/parsing/extractors/epub_extractor.py
sharepoint2text/parsing/extractors/html_extractor.py
sharepoint2text/parsing/extractors/mhtml_extractor.py
sharepoint2text/parsing/extractors/plain_extractor.py
sharepoint2text/parsing/extractors/serialization.py
sharepoint2text/parsing/extractors/mail/__init__.py
sharepoint2text/parsing/extractors/mail/eml_email_extractor.py
sharepoint2text/parsing/extractors/mail/mbox_email_extractor.py
sharepoint2text/parsing/extractors/mail/msg_email_extractor.py
sharepoint2text/parsing/extractors/ms_legacy/__init__.py
sharepoint2text/parsing/extractors/ms_legacy/doc_extractor.py
sharepoint2text/parsing/extractors/ms_legacy/ppt_extractor.py
sharepoint2text/parsing/extractors/ms_legacy/rtf_extractor.py
sharepoint2text/parsing/extractors/ms_legacy/xls_extractor.py
sharepoint2text/parsing/extractors/ms_modern/__init__.py
sharepoint2text/parsing/extractors/ms_modern/docx_extractor.py
sharepoint2text/parsing/extractors/ms_modern/pptx_extractor.py
sharepoint2text/parsing/extractors/ms_modern/xlsx_extractor.py
sharepoint2text/parsing/extractors/open_office/__init__.py
sharepoint2text/parsing/extractors/open_office/_shared.py
sharepoint2text/parsing/extractors/open_office/odf_extractor.py
sharepoint2text/parsing/extractors/open_office/odg_extractor.py
sharepoint2text/parsing/extractors/open_office/odp_extractor.py
sharepoint2text/parsing/extractors/open_office/ods_extractor.py
sharepoint2text/parsing/extractors/open_office/odt_extractor.py
sharepoint2text/parsing/extractors/pdf/__init__.py
sharepoint2text/parsing/extractors/pdf/_pypdf_aes_fallback.py
sharepoint_to_text-0.8.1.dist-info/METADATA
sharepoint_to_text-0.8.1.dist-info/WHEEL
sharepoint_to_text-0.8.1.dist-info/entry_points.txt
sharepoint_to_text-0.8.1.dist-info/licenses/LICENSE
sharepoint_to_text-0.8.1.dist-info/RECORD
