Metadata-Version: 2.4
Name: sharepoint-to-text
Version: 0.8.1
Summary: Text extraction library for typical file formats found in SharePoint repositories
Project-URL: Homepage, https://github.com/Horsmann/sharepoint-to-text
Project-URL: Documentation, https://github.com/Horsmann/sharepoint-to-text#readme
Project-URL: Repository, https://github.com/Horsmann/sharepoint-to-text.git
Project-URL: Issues, https://github.com/Horsmann/sharepoint-to-text/issues
Project-URL: Changelog, https://github.com/Horsmann/sharepoint-to-text/blob/main/CHANGELOG.md
Author-email: Tobias Horsmann <tobias.horsmann@gmail.com>
Maintainer-email: Tobias Horsmann <tobias.horsmann@gmail.com>
License-Expression: Apache-2.0
License-File: LICENSE
Keywords: aws-lambda,csv,doc,document-extraction,document-processing,docx,email,eml,json,llm,mbox,md,microsoft-office,msg,nlp,odp,ods,office,pdf,ppt,pptx,pure-python,rag,rtf,serverless,sharepoint,text-extraction,tsv,xls,xlsx
Classifier: Development Status :: 4 - Beta
Classifier: Intended Audience :: Developers
Classifier: Intended Audience :: Science/Research
Classifier: License :: OSI Approved :: Apache Software License
Classifier: Operating System :: OS Independent
Classifier: Programming Language :: Python :: 3
Classifier: Programming Language :: Python :: 3.10
Classifier: Programming Language :: Python :: 3.11
Classifier: Programming Language :: Python :: 3.12
Classifier: Programming Language :: Python :: 3.13
Classifier: Programming Language :: Python :: 3.14
Classifier: Topic :: Communications :: Email
Classifier: Topic :: Office/Business
Classifier: Topic :: Scientific/Engineering :: Artificial Intelligence
Classifier: Topic :: Software Development :: Libraries :: Python Modules
Classifier: Topic :: Text Processing
Classifier: Topic :: Text Processing :: Indexing
Classifier: Typing :: Typed
Requires-Python: >=3.10
Requires-Dist: charset-normalizer>=3.3.0
Requires-Dist: defusedxml>=0.7.1
Requires-Dist: mail-parser>=4.1.4
Requires-Dist: msg-parser>=1.2.0
Requires-Dist: olefile>=0.47
Requires-Dist: openpyxl>=3.1.5
Requires-Dist: pypdf<6.6.0,>=6.5.0
Requires-Dist: xlrd>=2.0.2
Provides-Extra: pdf-crypto
Requires-Dist: pycryptodome>=3.20.0; extra == 'pdf-crypto'
